pyconse23_sample_project-0.1.0.dist-info/METADATA
pyconse23_sample_project-0.1.0.dist-info/WHEEL
pyconse23_sample_project/__init__.py
pyconse23_sample_project-0.1.0.dist-info/RECORD
