Metadata-Version: 2.1
Name: pyconse23-sample-project
Version: 0.1.0
Summary: Sample project that gets the weather forecast for Stockholm
Author-Email: Yngve Mardal Moe <yngve.moe@bouvet.no>
License: MIT
Requires-Python: >=3.11
Requires-Dist: httpx>=0.25.0
Requires-Dist: plotille>=5.0.0
